bizstats_db_manager/__init__.py
bizstats_db_manager/base.py
bizstats_db_manager/celery_utils.py
bizstats_db_manager/config.py
bizstats_db_manager/health.py
bizstats_db_manager/manager.py
bizstats_db_manager/service.py
bizstats_db_manager-0.1.0.dist-info/METADATA
bizstats_db_manager-0.1.0.dist-info/WHEEL
bizstats_db_manager-0.1.0.dist-info/RECORD
