Metadata-Version: 2.4
Name: bizstats-db-manager
Version: 0.1.0
Summary: PostgreSQL database management with async support, connection pooling, and migration utilities
Project-URL: Homepage, https://github.com/absolut-e/bizstats-db-manager
Project-URL: Documentation, https://github.com/absolut-e/bizstats-db-manager#readme
Project-URL: Repository, https://github.com/absolut-e/bizstats-db-manager
Project-URL: Issues, https://github.com/absolut-e/bizstats-db-manager/issues
Author-email: "Absolut-e Data Com Inc." <account@absolut-e.com>
License-Expression: MIT
Keywords: alembic,async,asyncpg,connection-pool,database,migrations,postgresql,sqlalchemy
Classifier: Development Status :: 4 - Beta
Classifier: Framework :: AsyncIO
Classifier: Intended Audience :: Developers
Classifier: License :: OSI Approved :: MIT License
Classifier: Operating System :: OS Independent
Classifier: Programming Language :: Python :: 3
Classifier: Programming Language :: Python :: 3.11
Classifier: Programming Language :: Python :: 3.12
Classifier: Topic :: Database
Classifier: Topic :: Software Development :: Libraries :: Python Modules
Classifier: Typing :: Typed
Requires-Python: >=3.11
Requires-Dist: alembic>=1.13.0
Requires-Dist: asyncpg>=0.29.0
Requires-Dist: psycopg2-binary>=2.9.9
Requires-Dist: pydantic-settings>=2.0.0
Requires-Dist: pydantic>=2.0.0
Requires-Dist: sqlalchemy[asyncio]>=2.0.0
Provides-Extra: celery
Requires-Dist: celery>=5.3.0; extra == 'celery'
Provides-Extra: dev
Requires-Dist: black>=24.0.0; extra == 'dev'
Requires-Dist: mypy>=1.8.0; extra == 'dev'
Requires-Dist: pytest-asyncio>=0.23.0; extra == 'dev'
Requires-Dist: pytest-cov>=4.1.0; extra == 'dev'
Requires-Dist: pytest-mock>=3.12.0; extra == 'dev'
Requires-Dist: pytest>=8.0.0; extra == 'dev'
Requires-Dist: ruff>=0.1.0; extra == 'dev'
Provides-Extra: test
Requires-Dist: pytest-asyncio>=0.23.0; extra == 'test'
Requires-Dist: pytest-cov>=4.1.0; extra == 'test'
Requires-Dist: pytest-mock>=3.12.0; extra == 'test'
Requires-Dist: pytest>=8.0.0; extra == 'test'
Requires-Dist: testcontainers[postgres]>=3.7.0; extra == 'test'
